sblibs.py
sblibs/__init__.py
sblibs/main.py
sblibs/settings.py
sblibs/version.py
sblibs/aws/__init__.py
sblibs/aws/ec2.py
sblibs/display/__init__.py
sblibs/display/animation.py
sblibs/display/asciiart.py
sblibs/display/base.py
sblibs/display/color.py
sblibs/display/debugging.py
sblibs/display/decorator.py
sblibs/display/general.py
sblibs/display/stream.py
sblibs/utils/__init__.py
sblibs-0.0.9.dist-info/DESCRIPTION.rst
sblibs-0.0.9.dist-info/METADATA
sblibs-0.0.9.dist-info/RECORD
sblibs-0.0.9.dist-info/WHEEL
sblibs-0.0.9.dist-info/metadata.json
sblibs-0.0.9.dist-info/top_level.txt
