Metadata-Version: 2.0
Name: sblibs
Version: 0.0.9
Summary: sblibs package
Home-page: https://github.com/studyblue/sblibs
Author: Fred Vassard
Author-email: fred@studyblue.com
License: Copyright (c) 2012, Fred Vassard
Requires-Dist: nose
Requires-Dist: sphinx
Requires-Dist: recommonmark
Requires-Dist: boto
Requires-Dist: boto3
Requires-Dist: prettytable
